{"id": "X6cbmmOJZRA", "title": "Conjunto Primavera - Muero (Audio)", "formats": [{"asr": 48000, "filesize": 1473410, "format_id": "249", "format_note": "tiny", "fps": null, "height": null, "quality": 0, "tbr": 51.648, "url": "https://rr4---sn-0opoxu-ihv6.googlevideo.com/videoplayback?expire=1670688948&ei=VFyUY7v6H5aIkgadip_oCQ&ip=189.173.225.87&id=o-AFW7Rp6p35vgAk6-fBL-fAQ0-SfRE7H3WnB1rShRkFlV&itag=249&source=youtube&requiressl=yes&mh=ik&mm=31%2C29&mn=sn-0opoxu-ihv6%2Csn-q4fl6nz6&ms=au%2Crdu&mv=m&mvi=4&pcm2cms=yes&pl=24&gcr=mx&initcwndbps=896250&vprv=1&mime=audio%2Fwebm&ns=2bGxXg8GVqTE0hLH61FT-WgJ&gir=yes&clen=1473410&dur=228.221&lmt=1605404476630530&mt=1670666961&fvip=4&keepalive=yes&fexp=24001373%2C24007246&c=WEB&txp=1311222&n=WHwbY3eV_UXa3-_mb&sparams=expire%2Cei%2Cip%2Cid%2Citag%2Csource%2Crequiressl%2Cgcr%2Cvprv%2Cmime%2Cns%2Cgir%2Cclen%2Cdur%2Clmt&lsparams=mh%2Cmm%2Cmn%2Cms%2Cmv%2Cmvi%2Cpcm2cms%2Cpl%2Cinitcwndbps&lsig=AG3C_xAwRAIgZnrrH8-v-goaQ4QsrpIlSQs3UeAN-s3iHahLPy3--1UCIBmwB3sscLRTxbLWvyue4IEJPDLGPEf60Np4owc13fKB&sig=AOq0QJ8wRgIhAPyhg34vFzSvDqy5MEa_fqhlX6O6giRT4A1IoTpl9KfsAiEA1VMqx4k9-t_MkZhdK8Et1jClg9i20ucc5n4vJOcgGOY=", "width": null, "ext": "webm", "vcodec": "none", "acodec": "opus", "abr": 51.648, "downloader_options": {"http_chunk_size": 10485760}, "container": "webm_dash", "format": "249 - audio only (tiny)", "protocol": "https", "http_headers": {"User-Agent": "Mozilla/5.0 (Windows NT 10.0; Win64; x64) AppleWebKit/537.36 (KHTML, like Gecko) Chrome/73.0.3661.1 Safari/537.36", "Accept-Charset": "ISO-8859-1,utf-8;q=0.7,*;q=0.7", "Accept": "text/html,application/xhtml+xml,application/xml;q=0.9,*/*;q=0.8", "Accept-Encoding": "gzip, deflate", "Accept-Language": "en-us,en;q=0.5"}}, {"asr": 48000, "filesize": 1948993, "format_id": "250", "format_note": "tiny", "fps": null, "height": null, "quality": 0, "tbr": 68.319, "url": "https://rr4---sn-0opoxu-ihv6.googlevideo.com/videoplayback?expire=1670688948&ei=VFyUY7v6H5aIkgadip_oCQ&ip=189.173.225.87&id=o-AFW7Rp6p35vgAk6-fBL-fAQ0-SfRE7H3WnB1rShRkFlV&itag=250&source=youtube&requiressl=yes&mh=ik&mm=31%2C29&mn=sn-0opoxu-ihv6%2Csn-q4fl6nz6&ms=au%2Crdu&mv=m&mvi=4&pcm2cms=yes&pl=24&gcr=mx&initcwndbps=896250&vprv=1&mime=audio%2Fwebm&ns=2bGxXg8GVqTE0hLH61FT-WgJ&gir=yes&clen=1948993&dur=228.221&lmt=1605404475612520&mt=1670666961&fvip=4&keepalive=yes&fexp=24001373%2C24007246&c=WEB&txp=1311222&n=WHwbY3eV_UXa3-_mb&sparams=expire%2Cei%2Cip%2Cid%2Citag%2Csource%2Crequiressl%2Cgcr%2Cvprv%2Cmime%2Cns%2Cgir%2Cclen%2Cdur%2Clmt&lsparams=mh%2Cmm%2Cmn%2Cms%2Cmv%2Cmvi%2Cpcm2cms%2Cpl%2Cinitcwndbps&lsig=AG3C_xAwRQIhAKGCzOJoyIJk5gAbmIuFpXKjRiN7yMWSzW86N6YYAjoDAiBHGypZGsoS5t-LCAfrI7jeHeoS2chZ_hNOSbkoiAc95w%3D%3D&sig=AOq0QJ8wRAIgcF0kk0df7Wg70KyEl9NlsQqDdEfFCCZbhCeIqi1mk4kCIGpVAgGJOjQ6dox3089iNxmnOyfrfl5dAObLAXgBWGHQ", "width": null, "ext": "webm", "vcodec": "none", "acodec": "opus", "abr": 68.319, "downloader_options": {"http_chunk_size": 10485760}, "container": "webm_dash", "format": "250 - audio only (tiny)", "protocol": "https", "http_headers": {"User-Agent": "Mozilla/5.0 (Windows NT 10.0; Win64; x64) AppleWebKit/537.36 (KHTML, like Gecko) Chrome/73.0.3661.1 Safari/537.36", "Accept-Charset": "ISO-8859-1,utf-8;q=0.7,*;q=0.7", "Accept": "text/html,application/xhtml+xml,application/xml;q=0.9,*/*;q=0.8", "Accept-Encoding": "gzip, deflate", "Accept-Language": "en-us,en;q=0.5"}}, {"asr": 44100, "filesize": 3694686, "format_id": "140", "format_note": "tiny", "fps": null, "height": null, "quality": 0, "tbr": 129.494, "url": "https://rr4---sn-0opoxu-ihv6.googlevideo.com/videoplayback?expire=1670688948&ei=VFyUY7v6H5aIkgadip_oCQ&ip=189.173.225.87&id=o-AFW7Rp6p35vgAk6-fBL-fAQ0-SfRE7H3WnB1rShRkFlV&itag=140&source=youtube&requiressl=yes&mh=ik&mm=31%2C29&mn=sn-0opoxu-ihv6%2Csn-q4fl6nz6&ms=au%2Crdu&mv=m&mvi=4&pcm2cms=yes&pl=24&gcr=mx&initcwndbps=896250&vprv=1&mime=audio%2Fmp4&ns=2bGxXg8GVqTE0hLH61FT-WgJ&gir=yes&clen=3694686&dur=228.252&lmt=1605402220072989&mt=1670666961&fvip=4&keepalive=yes&fexp=24001373%2C24007246&c=WEB&txp=1311222&n=WHwbY3eV_UXa3-_mb&sparams=expire%2Cei%2Cip%2Cid%2Citag%2Csource%2Crequiressl%2Cgcr%2Cvprv%2Cmime%2Cns%2Cgir%2Cclen%2Cdur%2Clmt&lsparams=mh%2Cmm%2Cmn%2Cms%2Cmv%2Cmvi%2Cpcm2cms%2Cpl%2Cinitcwndbps&lsig=AG3C_xAwRgIhAOcgU7nUKC_9NOTxtzJuAdK5N1lgDxurTu4kfPU6IEjYAiEAu57EK4-qG9LF1sWDahwP-9ZHBJ4Bkxs1fhlmU2oykPk%3D&sig=AOq0QJ8wRQIgWxSdDTp6Grnu4IrEPNzDHT7pxqzdVj5nNvkxwU2VfjwCIQCKqdKppkKDVFP5PIaKItiL_Ns2VSmwHuyhEJqFn5rbBQ==", "width": null, "ext": "m4a", "vcodec": "none", "acodec": "mp4a.40.2", "abr": 129.494, "downloader_options": {"http_chunk_size": 10485760}, "container": "m4a_dash", "format": "140 - audio only (tiny)", "protocol": "https", "http_headers": {"User-Agent": "Mozilla/5.0 (Windows NT 10.0; Win64; x64) AppleWebKit/537.36 (KHTML, like Gecko) Chrome/73.0.3661.1 Safari/537.36", "Accept-Charset": "ISO-8859-1,utf-8;q=0.7,*;q=0.7", "Accept": "text/html,application/xhtml+xml,application/xml;q=0.9,*/*;q=0.8", "Accept-Encoding": "gzip, deflate", "Accept-Language": "en-us,en;q=0.5"}}, {"asr": 48000, "filesize": 3839571, "format_id": "251", "format_note": "tiny", "fps": null, "height": null, "quality": 0, "tbr": 134.591, "url": "https://rr4---sn-0opoxu-ihv6.googlevideo.com/videoplayback?expire=1670688948&ei=VFyUY7v6H5aIkgadip_oCQ&ip=189.173.225.87&id=o-AFW7Rp6p35vgAk6-fBL-fAQ0-SfRE7H3WnB1rShRkFlV&itag=251&source=youtube&requiressl=yes&mh=ik&mm=31%2C29&mn=sn-0opoxu-ihv6%2Csn-q4fl6nz6&ms=au%2Crdu&mv=m&mvi=4&pcm2cms=yes&pl=24&gcr=mx&initcwndbps=896250&vprv=1&mime=audio%2Fwebm&ns=2bGxXg8GVqTE0hLH61FT-WgJ&gir=yes&clen=3839571&dur=228.221&lmt=1605404476164991&mt=1670666961&fvip=4&keepalive=yes&fexp=24001373%2C24007246&c=WEB&txp=1311222&n=WHwbY3eV_UXa3-_mb&sparams=expire%2Cei%2Cip%2Cid%2Citag%2Csource%2Crequiressl%2Cgcr%2Cvprv%2Cmime%2Cns%2Cgir%2Cclen%2Cdur%2Clmt&lsparams=mh%2Cmm%2Cmn%2Cms%2Cmv%2Cmvi%2Cpcm2cms%2Cpl%2Cinitcwndbps&lsig=AG3C_xAwRAIgRtbeAD5K5bjCcHoDnp5RtGbOMJH2hhBEk4cgQIYxh4oCIFCnO5_T4ZBeyXglarhp2OUcxMXRkVhAAPwL84SUAo7F&sig=AOq0QJ8wRAIgXRJvIwnpqZoFMq0CQC-xSoroIGpVRWOGfZ6-bN0Tw-QCIClb7zYUr-HXifiikdL670B-3QUfu_y3QRr02jnNMmIp", "width": null, "ext": "webm", "vcodec": "none", "acodec": "opus", "abr": 134.591, "downloader_options": {"http_chunk_size": 10485760}, "container": "webm_dash", "format": "251 - audio only (tiny)", "protocol": "https", "http_headers": {"User-Agent": "Mozilla/5.0 (Windows NT 10.0; Win64; x64) AppleWebKit/537.36 (KHTML, like Gecko) Chrome/73.0.3661.1 Safari/537.36", "Accept-Charset": "ISO-8859-1,utf-8;q=0.7,*;q=0.7", "Accept": "text/html,application/xhtml+xml,application/xml;q=0.9,*/*;q=0.8", "Accept-Encoding": "gzip, deflate", "Accept-Language": "en-us,en;q=0.5"}}, {"asr": null, "filesize": 658359, "format_id": "278", "format_note": "144p", "fps": 24, "height": 144, "quality": 0, "tbr": 23.081, "url": "https://rr4---sn-0opoxu-ihv6.googlevideo.com/videoplayback?expire=1670688948&ei=VFyUY7v6H5aIkgadip_oCQ&ip=189.173.225.87&id=o-AFW7Rp6p35vgAk6-fBL-fAQ0-SfRE7H3WnB1rShRkFlV&itag=278&aitags=133%2C134%2C135%2C136%2C137%2C160%2C242%2C243%2C244%2C247%2C248%2C278&source=youtube&requiressl=yes&mh=ik&mm=31%2C29&mn=sn-0opoxu-ihv6%2Csn-q4fl6nz6&ms=au%2Crdu&mv=m&mvi=4&pcm2cms=yes&pl=24&gcr=mx&initcwndbps=896250&vprv=1&mime=video%2Fwebm&ns=2bGxXg8GVqTE0hLH61FT-WgJ&gir=yes&clen=658359&dur=228.186&lmt=1605405968510799&mt=1670666961&fvip=4&keepalive=yes&fexp=24001373%2C24007246&c=WEB&txp=1311222&n=WHwbY3eV_UXa3-_mb&sparams=expire%2Cei%2Cip%2Cid%2Caitags%2Csource%2Crequiressl%2Cgcr%2Cvprv%2Cmime%2Cns%2Cgir%2Cclen%2Cdur%2Clmt&lsparams=mh%2Cmm%2Cmn%2Cms%2Cmv%2Cmvi%2Cpcm2cms%2Cpl%2Cinitcwndbps&lsig=AG3C_xAwRAIgCUPlRu0iH22FIQsxHEsv8C9GMBBN881ngHNrywRR2e8CIBM8m1y3EbTtm5GPCZ4Cp-fu2sXN5OkQxDAoKy4YVotz&sig=AOq0QJ8wRgIhAI2qspXwzYC8bm1PgC-s0b1eFaH_mCr8oxVnIbhXG6BQAiEA8A76Y1vAQzz8-KKiYhoirLPtikkbzn6onZZR1i8VaHY=", "width": 256, "ext": "webm", "vcodec": "vp9", "acodec": "none", "vbr": 23.081, "downloader_options": {"http_chunk_size": 10485760}, "container": "webm_dash", "format": "278 - 256x144 (144p)", "protocol": "https", "http_headers": {"User-Agent": "Mozilla/5.0 (Windows NT 10.0; Win64; x64) AppleWebKit/537.36 (KHTML, like Gecko) Chrome/73.0.3661.1 Safari/537.36", "Accept-Charset": "ISO-8859-1,utf-8;q=0.7,*;q=0.7", "Accept": "text/html,application/xhtml+xml,application/xml;q=0.9,*/*;q=0.8", "Accept-Encoding": "gzip, deflate", "Accept-Language": "en-us,en;q=0.5"}}, {"asr": null, "filesize": 3027822, "format_id": "160", "format_note": "144p", "fps": 24, "height": 144, "quality": 0, "tbr": 106.152, "url": "https://rr4---sn-0opoxu-ihv6.googlevideo.com/videoplayback?expire=1670688948&ei=VFyUY7v6H5aIkgadip_oCQ&ip=189.173.225.87&id=o-AFW7Rp6p35vgAk6-fBL-fAQ0-SfRE7H3WnB1rShRkFlV&itag=160&aitags=133%2C134%2C135%2C136%2C137%2C160%2C242%2C243%2C244%2C247%2C248%2C278&source=youtube&requiressl=yes&mh=ik&mm=31%2C29&mn=sn-0opoxu-ihv6%2Csn-q4fl6nz6&ms=au%2Crdu&mv=m&mvi=4&pcm2cms=yes&pl=24&gcr=mx&initcwndbps=896250&vprv=1&mime=video%2Fmp4&ns=2bGxXg8GVqTE0hLH61FT-WgJ&gir=yes&clen=3027822&dur=228.186&lmt=1605402269369544&mt=1670666961&fvip=4&keepalive=yes&fexp=24001373%2C24007246&c=WEB&txp=1311222&n=WHwbY3eV_UXa3-_mb&sparams=expire%2Cei%2Cip%2Cid%2Caitags%2Csource%2Crequiressl%2Cgcr%2Cvprv%2Cmime%2Cns%2Cgir%2Cclen%2Cdur%2Clmt&lsparams=mh%2Cmm%2Cmn%2Cms%2Cmv%2Cmvi%2Cpcm2cms%2Cpl%2Cinitcwndbps&lsig=AG3C_xAwRAIgDdTT4EDFZMwcRUvdf0F52NTgYP0On6uGqN1ntZ6HgcQCICxGjnRK9UZm7auVk351Ua14Dr0hOV2EYYjzBAGN9se0&sig=AOq0QJ8wRQIgScIPPFZJ3quIGuGZQGv_wHYjKm7ey377YZrkQ1gRQx0CIQDph4XcuKCbgwHK9xDFymujqC0cFUeQpXstewTFFujnhQ==", "width": 256, "ext": "mp4", "vcodec": "avc1.4d400c", "acodec": "none", "vbr": 106.152, "downloader_options": {"http_chunk_size": 10485760}, "container": "mp4_dash", "format": "160 - 256x144 (144p)", "protocol": "https", "http_headers": {"User-Agent": "Mozilla/5.0 (Windows NT 10.0; Win64; x64) AppleWebKit/537.36 (KHTML, like Gecko) Chrome/73.0.3661.1 Safari/537.36", "Accept-Charset": "ISO-8859-1,utf-8;q=0.7,*;q=0.7", "Accept": "text/html,application/xhtml+xml,application/xml;q=0.9,*/*;q=0.8", "Accept-Encoding": "gzip, deflate", "Accept-Language": "en-us,en;q=0.5"}}, {"asr": null, "filesize": 956820, "format_id": "242", "format_note": "240p", "fps": 24, "height": 240, "quality": 1, "tbr": 33.545, "url": "https://rr4---sn-0opoxu-ihv6.googlevideo.com/videoplayback?expire=1670688948&ei=VFyUY7v6H5aIkgadip_oCQ&ip=189.173.225.87&id=o-AFW7Rp6p35vgAk6-fBL-fAQ0-SfRE7H3WnB1rShRkFlV&itag=242&aitags=133%2C134%2C135%2C136%2C137%2C160%2C242%2C243%2C244%2C247%2C248%2C278&source=youtube&requiressl=yes&mh=ik&mm=31%2C29&mn=sn-0opoxu-ihv6%2Csn-q4fl6nz6&ms=au%2Crdu&mv=m&mvi=4&pcm2cms=yes&pl=24&gcr=mx&initcwndbps=896250&vprv=1&mime=video%2Fwebm&ns=2bGxXg8GVqTE0hLH61FT-WgJ&gir=yes&clen=956820&dur=228.186&lmt=1605405968566074&mt=1670666961&fvip=4&keepalive=yes&fexp=24001373%2C24007246&c=WEB&txp=1311222&n=WHwbY3eV_UXa3-_mb&sparams=expire%2Cei%2Cip%2Cid%2Caitags%2Csource%2Crequiressl%2Cgcr%2Cvprv%2Cmime%2Cns%2Cgir%2Cclen%2Cdur%2Clmt&lsparams=mh%2Cmm%2Cmn%2Cms%2Cmv%2Cmvi%2Cpcm2cms%2Cpl%2Cinitcwndbps&lsig=AG3C_xAwRgIhAJkYt2smjJiJM8n2ywmu2vBcjbd0u3-P28Qm9VaH3C1rAiEAnzUlsvq0yNCkdACNhf4eJv2BGvjtss68Gk-EqWYahLc%3D&sig=AOq0QJ8wRQIgQuCT4PjXgAs-C2kjU_Gbrqfopzti5pcE1njmrqdtnGYCIQCSBQmSpVmMJEZsCliGWYyrwiCnIQOxIVcUAYzIacufnw==", "width": 426, "ext": "webm", "vcodec": "vp9", "acodec": "none", "vbr": 33.545, "downloader_options": {"http_chunk_size": 10485760}, "container": "webm_dash", "format": "242 - 426x240 (240p)", "protocol": "https", "http_headers": {"User-Agent": "Mozilla/5.0 (Windows NT 10.0; Win64; x64) AppleWebKit/537.36 (KHTML, like Gecko) Chrome/73.0.3661.1 Safari/537.36", "Accept-Charset": "ISO-8859-1,utf-8;q=0.7,*;q=0.7", "Accept": "text/html,application/xhtml+xml,application/xml;q=0.9,*/*;q=0.8", "Accept-Encoding": "gzip, deflate", "Accept-Language": "en-us,en;q=0.5"}}, {"asr": null, "filesize": 7165464, "format_id": "133", "format_note": "240p", "fps": 24, "height": 240, "quality": 1, "tbr": 251.214, "url": "https://rr4---sn-0opoxu-ihv6.googlevideo.com/videoplayback?expire=1670688948&ei=VFyUY7v6H5aIkgadip_oCQ&ip=189.173.225.87&id=o-AFW7Rp6p35vgAk6-fBL-fAQ0-SfRE7H3WnB1rShRkFlV&itag=133&aitags=133%2C134%2C135%2C136%2C137%2C160%2C242%2C243%2C244%2C247%2C248%2C278&source=youtube&requiressl=yes&mh=ik&mm=31%2C29&mn=sn-0opoxu-ihv6%2Csn-q4fl6nz6&ms=au%2Crdu&mv=m&mvi=4&pcm2cms=yes&pl=24&gcr=mx&initcwndbps=896250&vprv=1&mime=video%2Fmp4&ns=2bGxXg8GVqTE0hLH61FT-WgJ&gir=yes&clen=7165464&dur=228.186&lmt=1605402269371983&mt=1670666961&fvip=4&keepalive=yes&fexp=24001373%2C24007246&c=WEB&txp=1311222&n=WHwbY3eV_UXa3-_mb&sparams=expire%2Cei%2Cip%2Cid%2Caitags%2Csource%2Crequiressl%2Cgcr%2Cvprv%2Cmime%2Cns%2Cgir%2Cclen%2Cdur%2Clmt&lsparams=mh%2Cmm%2Cmn%2Cms%2Cmv%2Cmvi%2Cpcm2cms%2Cpl%2Cinitcwndbps&lsig=AG3C_xAwRQIhALUcZ84nrLw76zD5eJBqtPCIZq22geqITpMPCMcrXxfWAiAtU6bzH1IBrq65020LcoQ0eZo1t5dEY7X-OcfsxnZ6dQ%3D%3D&sig=AOq0QJ8wRQIgAhtiBqe9SClr-8HG2gQvmX02UiPSBm2SKz-nJxq6rS0CIQC5a7Ag7xN4alvh7aQMkUSMNnLbIsqkJb6qbOwLngJcPw==", "width": 426, "ext": "mp4", "vcodec": "avc1.4d4015", "acodec": "none", "vbr": 251.214, "downloader_options": {"http_chunk_size": 10485760}, "container": "mp4_dash", "format": "133 - 426x240 (240p)", "protocol": "https", "http_headers": {"User-Agent": "Mozilla/5.0 (Windows NT 10.0; Win64; x64) AppleWebKit/537.36 (KHTML, like Gecko) Chrome/73.0.3661.1 Safari/537.36", "Accept-Charset": "ISO-8859-1,utf-8;q=0.7,*;q=0.7", "Accept": "text/html,application/xhtml+xml,application/xml;q=0.9,*/*;q=0.8", "Accept-Encoding": "gzip, deflate", "Accept-Language": "en-us,en;q=0.5"}}, {"asr": null, "filesize": 1685041, "format_id": "243", "format_note": "360p", "fps": 24, "height": 360, "quality": 2, "tbr": 59.076, "url": "https://rr4---sn-0opoxu-ihv6.googlevideo.com/videoplayback?expire=1670688948&ei=VFyUY7v6H5aIkgadip_oCQ&ip=189.173.225.87&id=o-AFW7Rp6p35vgAk6-fBL-fAQ0-SfRE7H3WnB1rShRkFlV&itag=243&aitags=133%2C134%2C135%2C136%2C137%2C160%2C242%2C243%2C244%2C247%2C248%2C278&source=youtube&requiressl=yes&mh=ik&mm=31%2C29&mn=sn-0opoxu-ihv6%2Csn-q4fl6nz6&ms=au%2Crdu&mv=m&mvi=4&pcm2cms=yes&pl=24&gcr=mx&initcwndbps=896250&vprv=1&mime=video%2Fwebm&ns=2bGxXg8GVqTE0hLH61FT-WgJ&gir=yes&clen=1685041&dur=228.186&lmt=1605405968531430&mt=1670666961&fvip=4&keepalive=yes&fexp=24001373%2C24007246&c=WEB&txp=1311222&n=WHwbY3eV_UXa3-_mb&sparams=expire%2Cei%2Cip%2Cid%2Caitags%2Csource%2Crequiressl%2Cgcr%2Cvprv%2Cmime%2Cns%2Cgir%2Cclen%2Cdur%2Clmt&lsparams=mh%2Cmm%2Cmn%2Cms%2Cmv%2Cmvi%2Cpcm2cms%2Cpl%2Cinitcwndbps&lsig=AG3C_xAwRQIhAJ3ta2aXcQLOTHAuLkUIIucpz1-5rwxm64X1owycOIo9AiA_S1-0ojqOk7QN290CxqU_ftRlp6bV0KaCoyJyixwfOw%3D%3D&sig=AOq0QJ8wRAIgY83uy6r8CJExoQ_6WlfW2fTGjblUILHsRvFk2i7ZoLACIBeR8KxyrrxtzGnPrERxxvPDg_a1STcU6NXggdRZendp", "width": 640, "ext": "webm", "vcodec": "vp9", "acodec": "none", "vbr": 59.076, "downloader_options": {"http_chunk_size": 10485760}, "container": "webm_dash", "format": "243 - 640x360 (360p)", "protocol": "https", "http_headers": {"User-Agent": "Mozilla/5.0 (Windows NT 10.0; Win64; x64) AppleWebKit/537.36 (KHTML, like Gecko) Chrome/73.0.3661.1 Safari/537.36", "Accept-Charset": "ISO-8859-1,utf-8;q=0.7,*;q=0.7", "Accept": "text/html,application/xhtml+xml,application/xml;q=0.9,*/*;q=0.8", "Accept-Encoding": "gzip, deflate", "Accept-Language": "en-us,en;q=0.5"}}, {"asr": null, "filesize": 2055977, "format_id": "134", "format_note": "360p", "fps": 24, "height": 360, "quality": 2, "tbr": 72.08, "url": "https://rr4---sn-0opoxu-ihv6.googlevideo.com/videoplayback?expire=1670688948&ei=VFyUY7v6H5aIkgadip_oCQ&ip=189.173.225.87&id=o-AFW7Rp6p35vgAk6-fBL-fAQ0-SfRE7H3WnB1rShRkFlV&itag=134&aitags=133%2C134%2C135%2C136%2C137%2C160%2C242%2C243%2C244%2C247%2C248%2C278&source=youtube&requiressl=yes&mh=ik&mm=31%2C29&mn=sn-0opoxu-ihv6%2Csn-q4fl6nz6&ms=au%2Crdu&mv=m&mvi=4&pcm2cms=yes&pl=24&gcr=mx&initcwndbps=896250&vprv=1&mime=video%2Fmp4&ns=2bGxXg8GVqTE0hLH61FT-WgJ&gir=yes&clen=2055977&dur=228.186&lmt=1605402269373872&mt=1670666961&fvip=4&keepalive=yes&fexp=24001373%2C24007246&c=WEB&txp=1311222&n=WHwbY3eV_UXa3-_mb&sparams=expire%2Cei%2Cip%2Cid%2Caitags%2Csource%2Crequiressl%2Cgcr%2Cvprv%2Cmime%2Cns%2Cgir%2Cclen%2Cdur%2Clmt&lsparams=mh%2Cmm%2Cmn%2Cms%2Cmv%2Cmvi%2Cpcm2cms%2Cpl%2Cinitcwndbps&lsig=AG3C_xAwRQIhANGhYSRE96RUDpRr6B4fmubvCMd4lp557y4D-U_gEKlWAiAZ-x-WZAKFKhfg_SggU2sGiw0GU_E6wKMyMZqwn-i15g%3D%3D&sig=AOq0QJ8wRgIhAPUSfTLdx-se_TgPxeoa_BhdYCEzmHO0V9pzKe8WdiRIAiEAhtu3v5DHy8rmnCkGKWAJrzMfnPUaU69M5WkhXm_6i_o=", "width": 640, "ext": "mp4", "vcodec": "avc1.4d401e", "acodec": "none", "vbr": 72.08, "downloader_options": {"http_chunk_size": 10485760}, "container": "mp4_dash", "format": "134 - 640x360 (360p)", "protocol": "https", "http_headers": {"User-Agent": "Mozilla/5.0 (Windows NT 10.0; Win64; x64) AppleWebKit/537.36 (KHTML, like Gecko) Chrome/73.0.3661.1 Safari/537.36", "Accept-Charset": "ISO-8859-1,utf-8;q=0.7,*;q=0.7", "Accept": "text/html,application/xhtml+xml,application/xml;q=0.9,*/*;q=0.8", "Accept-Encoding": "gzip, deflate", "Accept-Language": "en-us,en;q=0.5"}}, {"asr": null, "filesize": 2667235, "format_id": "244", "format_note": "480p", "fps": 24, "height": 480, "quality": 3, "tbr": 93.51, "url": "https://rr4---sn-0opoxu-ihv6.googlevideo.com/videoplayback?expire=1670688948&ei=VFyUY7v6H5aIkgadip_oCQ&ip=189.173.225.87&id=o-AFW7Rp6p35vgAk6-fBL-fAQ0-SfRE7H3WnB1rShRkFlV&itag=244&aitags=133%2C134%2C135%2C136%2C137%2C160%2C242%2C243%2C244%2C247%2C248%2C278&source=youtube&requiressl=yes&mh=ik&mm=31%2C29&mn=sn-0opoxu-ihv6%2Csn-q4fl6nz6&ms=au%2Crdu&mv=m&mvi=4&pcm2cms=yes&pl=24&gcr=mx&initcwndbps=896250&vprv=1&mime=video%2Fwebm&ns=2bGxXg8GVqTE0hLH61FT-WgJ&gir=yes&clen=2667235&dur=228.186&lmt=1605405968535499&mt=1670666961&fvip=4&keepalive=yes&fexp=24001373%2C24007246&c=WEB&txp=1311222&n=WHwbY3eV_UXa3-_mb&sparams=expire%2Cei%2Cip%2Cid%2Caitags%2Csource%2Crequiressl%2Cgcr%2Cvprv%2Cmime%2Cns%2Cgir%2Cclen%2Cdur%2Clmt&lsparams=mh%2Cmm%2Cmn%2Cms%2Cmv%2Cmvi%2Cpcm2cms%2Cpl%2Cinitcwndbps&lsig=AG3C_xAwRgIhAJ8YUqYP4Vzvi72Gqrz2r7g2ZZLGz_bquXnU42RM6b5gAiEAjxRIeMBt0NgIBUeefC9uvCoKKzHklg1y0C9cl7AeE40%3D&sig=AOq0QJ8wRQIhAILcYxthxeY03N8Bg03kJP7OgDt31ry1tpoU40YBP8vVAiBRS9yM_9AHyPh563Ix1qUdLRuLZ3J3nf9Zl_Jwg-SE6w==", "width": 854, "ext": "webm", "vcodec": "vp9", "acodec": "none", "vbr": 93.51, "downloader_options": {"http_chunk_size": 10485760}, "container": "webm_dash", "format": "244 - 854x480 (480p)", "protocol": "https", "http_headers": {"User-Agent": "Mozilla/5.0 (Windows NT 10.0; Win64; x64) AppleWebKit/537.36 (KHTML, like Gecko) Chrome/73.0.3661.1 Safari/537.36", "Accept-Charset": "ISO-8859-1,utf-8;q=0.7,*;q=0.7", "Accept": "text/html,application/xhtml+xml,application/xml;q=0.9,*/*;q=0.8", "Accept-Encoding": "gzip, deflate", "Accept-Language": "en-us,en;q=0.5"}}, {"asr": null, "filesize": 4450542, "format_id": "135", "format_note": "480p", "fps": 24, "height": 480, "quality": 3, "tbr": 156.032, "url": "https://rr4---sn-0opoxu-ihv6.googlevideo.com/videoplayback?expire=1670688948&ei=VFyUY7v6H5aIkgadip_oCQ&ip=189.173.225.87&id=o-AFW7Rp6p35vgAk6-fBL-fAQ0-SfRE7H3WnB1rShRkFlV&itag=135&aitags=133%2C134%2C135%2C136%2C137%2C160%2C242%2C243%2C244%2C247%2C248%2C278&source=youtube&requiressl=yes&mh=ik&mm=31%2C29&mn=sn-0opoxu-ihv6%2Csn-q4fl6nz6&ms=au%2Crdu&mv=m&mvi=4&pcm2cms=yes&pl=24&gcr=mx&initcwndbps=896250&vprv=1&mime=video%2Fmp4&ns=2bGxXg8GVqTE0hLH61FT-WgJ&gir=yes&clen=4450542&dur=228.186&lmt=1605402269369197&mt=1670666961&fvip=4&keepalive=yes&fexp=24001373%2C24007246&c=WEB&txp=1311222&n=WHwbY3eV_UXa3-_mb&sparams=expire%2Cei%2Cip%2Cid%2Caitags%2Csource%2Crequiressl%2Cgcr%2Cvprv%2Cmime%2Cns%2Cgir%2Cclen%2Cdur%2Clmt&lsparams=mh%2Cmm%2Cmn%2Cms%2Cmv%2Cmvi%2Cpcm2cms%2Cpl%2Cinitcwndbps&lsig=AG3C_xAwRAIgPgsrf1Tni4WCSebQK0k8DinAABz96QvyFzc4aMXxvyoCID9FEpCFGcgVoMCcoPZfNHPSwYayVNRFutw8PCQ-A5M8&sig=AOq0QJ8wRQIhAPYrx3Q3AasknjzenIZ-uOyGWjPJptrN3k9TlDKrJC2AAiADsicHXYFPe60gfaKUDeNOG_mMerUKj6RhT8IchygqNA==", "width": 854, "ext": "mp4", "vcodec": "avc1.4d401e", "acodec": "none", "vbr": 156.032, "downloader_options": {"http_chunk_size": 10485760}, "container": "mp4_dash", "format": "135 - 854x480 (480p)", "protocol": "https", "http_headers": {"User-Agent": "Mozilla/5.0 (Windows NT 10.0; Win64; x64) AppleWebKit/537.36 (KHTML, like Gecko) Chrome/73.0.3661.1 Safari/537.36", "Accept-Charset": "ISO-8859-1,utf-8;q=0.7,*;q=0.7", "Accept": "text/html,application/xhtml+xml,application/xml;q=0.9,*/*;q=0.8", "Accept-Encoding": "gzip, deflate", "Accept-Language": "en-us,en;q=0.5"}}, {"asr": null, "filesize": 5668176, "format_id": "247", "format_note": "720p", "fps": 24, "height": 720, "quality": 4, "tbr": 198.721, "url": "https://rr4---sn-0opoxu-ihv6.googlevideo.com/videoplayback?expire=1670688948&ei=VFyUY7v6H5aIkgadip_oCQ&ip=189.173.225.87&id=o-AFW7Rp6p35vgAk6-fBL-fAQ0-SfRE7H3WnB1rShRkFlV&itag=247&aitags=133%2C134%2C135%2C136%2C137%2C160%2C242%2C243%2C244%2C247%2C248%2C278&source=youtube&requiressl=yes&mh=ik&mm=31%2C29&mn=sn-0opoxu-ihv6%2Csn-q4fl6nz6&ms=au%2Crdu&mv=m&mvi=4&pcm2cms=yes&pl=24&gcr=mx&initcwndbps=896250&vprv=1&mime=video%2Fwebm&ns=2bGxXg8GVqTE0hLH61FT-WgJ&gir=yes&clen=5668176&dur=228.186&lmt=1605405968571932&mt=1670666961&fvip=4&keepalive=yes&fexp=24001373%2C24007246&c=WEB&txp=1311222&n=WHwbY3eV_UXa3-_mb&sparams=expire%2Cei%2Cip%2Cid%2Caitags%2Csource%2Crequiressl%2Cgcr%2Cvprv%2Cmime%2Cns%2Cgir%2Cclen%2Cdur%2Clmt&lsparams=mh%2Cmm%2Cmn%2Cms%2Cmv%2Cmvi%2Cpcm2cms%2Cpl%2Cinitcwndbps&lsig=AG3C_xAwRAIgJxt-cjKzStsXVBCrqs4Ns8omWgYO344Rqv0-e_bHCGICIHo61xD6jG7pm9hTAMy9F6gaJ_O8-Bl8F8hexzjbX3eQ&sig=AOq0QJ8wRgIhANKB_I52m_AfCxIC-eP6gPC8MQ0gVPkIRpb6FCF9J3DOAiEAinXWgqPmFB13YYwXrCDOab9L__Lw0TV580qIfZQsSIs=", "width": 1280, "ext": "webm", "vcodec": "vp9", "acodec": "none", "vbr": 198.721, "downloader_options": {"http_chunk_size": 10485760}, "container": "webm_dash", "format": "247 - 1280x720 (720p)", "protocol": "https", "http_headers": {"User-Agent": "Mozilla/5.0 (Windows NT 10.0; Win64; x64) AppleWebKit/537.36 (KHTML, like Gecko) Chrome/73.0.3661.1 Safari/537.36", "Accept-Charset": "ISO-8859-1,utf-8;q=0.7,*;q=0.7", "Accept": "text/html,application/xhtml+xml,application/xml;q=0.9,*/*;q=0.8", "Accept-Encoding": "gzip, deflate", "Accept-Language": "en-us,en;q=0.5"}}, {"asr": null, "filesize": 9569712, "format_id": "136", "format_note": "720p", "fps": 24, "height": 720, "quality": 4, "tbr": 335.505, "url": "https://rr4---sn-0opoxu-ihv6.googlevideo.com/videoplayback?expire=1670688948&ei=VFyUY7v6H5aIkgadip_oCQ&ip=189.173.225.87&id=o-AFW7Rp6p35vgAk6-fBL-fAQ0-SfRE7H3WnB1rShRkFlV&itag=136&aitags=133%2C134%2C135%2C136%2C137%2C160%2C242%2C243%2C244%2C247%2C248%2C278&source=youtube&requiressl=yes&mh=ik&mm=31%2C29&mn=sn-0opoxu-ihv6%2Csn-q4fl6nz6&ms=au%2Crdu&mv=m&mvi=4&pcm2cms=yes&pl=24&gcr=mx&initcwndbps=896250&vprv=1&mime=video%2Fmp4&ns=2bGxXg8GVqTE0hLH61FT-WgJ&gir=yes&clen=9569712&dur=228.186&lmt=1605402269460804&mt=1670666961&fvip=4&keepalive=yes&fexp=24001373%2C24007246&c=WEB&txp=1311222&n=WHwbY3eV_UXa3-_mb&sparams=expire%2Cei%2Cip%2Cid%2Caitags%2Csource%2Crequiressl%2Cgcr%2Cvprv%2Cmime%2Cns%2Cgir%2Cclen%2Cdur%2Clmt&lsparams=mh%2Cmm%2Cmn%2Cms%2Cmv%2Cmvi%2Cpcm2cms%2Cpl%2Cinitcwndbps&lsig=AG3C_xAwRAIgQ62xlV8rgHV8LYCUj3gclMk4JGea-ZjbgBigkoDmB1cCIEOfhcvtGVUISaDkyadFhAQD0sumCkPIU3stFXEm5KPz&sig=AOq0QJ8wRgIhAMG-J2fpv1pMKWFyuAHJbzMZSseazUb9_F1XlTKihRXaAiEAggnj7x1xZR0k3BbDsOPBgTYbSx1HPiFOp7GaKL6aJKg=", "width": 1280, "ext": "mp4", "vcodec": "avc1.4d401f", "acodec": "none", "vbr": 335.505, "downloader_options": {"http_chunk_size": 10485760}, "container": "mp4_dash", "format": "136 - 1280x720 (720p)", "protocol": "https", "http_headers": {"User-Agent": "Mozilla/5.0 (Windows NT 10.0; Win64; x64) AppleWebKit/537.36 (KHTML, like Gecko) Chrome/73.0.3661.1 Safari/537.36", "Accept-Charset": "ISO-8859-1,utf-8;q=0.7,*;q=0.7", "Accept": "text/html,application/xhtml+xml,application/xml;q=0.9,*/*;q=0.8", "Accept-Encoding": "gzip, deflate", "Accept-Language": "en-us,en;q=0.5"}}, {"asr": null, "filesize": 10335210, "format_id": "248", "format_note": "1080p", "fps": 24, "height": 1080, "quality": 5, "tbr": 362.343, "url": "https://rr4---sn-0opoxu-ihv6.googlevideo.com/videoplayback?expire=1670688948&ei=VFyUY7v6H5aIkgadip_oCQ&ip=189.173.225.87&id=o-AFW7Rp6p35vgAk6-fBL-fAQ0-SfRE7H3WnB1rShRkFlV&itag=248&aitags=133%2C134%2C135%2C136%2C137%2C160%2C242%2C243%2C244%2C247%2C248%2C278&source=youtube&requiressl=yes&mh=ik&mm=31%2C29&mn=sn-0opoxu-ihv6%2Csn-q4fl6nz6&ms=au%2Crdu&mv=m&mvi=4&pcm2cms=yes&pl=24&gcr=mx&initcwndbps=896250&vprv=1&mime=video%2Fwebm&ns=2bGxXg8GVqTE0hLH61FT-WgJ&gir=yes&clen=10335210&dur=228.186&lmt=1605405968604016&mt=1670666961&fvip=4&keepalive=yes&fexp=24001373%2C24007246&c=WEB&txp=1311222&n=WHwbY3eV_UXa3-_mb&sparams=expire%2Cei%2Cip%2Cid%2Caitags%2Csource%2Crequiressl%2Cgcr%2Cvprv%2Cmime%2Cns%2Cgir%2Cclen%2Cdur%2Clmt&lsparams=mh%2Cmm%2Cmn%2Cms%2Cmv%2Cmvi%2Cpcm2cms%2Cpl%2Cinitcwndbps&lsig=AG3C_xAwRQIgJCmTeS-VO68MimftKpC-V8h1TZBJyHRa8bxBhoDAXZMCIQD6iTI_Vyp9onb7DNjTRr3-iMrc1Y0my-vUSU0TFHWdjQ%3D%3D&sig=AOq0QJ8wRQIhAK_DcfwtDVnGziG1KFqUQEICFaG1ePAFnPWHxwH-dc2aAiAlhVPUaaMcyXvZhv9uCrHxNwsl3V4686-1dGjIsYxgqg==", "width": 1920, "ext": "webm", "vcodec": "vp9", "acodec": "none", "vbr": 362.343, "downloader_options": {"http_chunk_size": 10485760}, "container": "webm_dash", "format": "248 - 1920x1080 (1080p)", "protocol": "https", "http_headers": {"User-Agent": "Mozilla/5.0 (Windows NT 10.0; Win64; x64) AppleWebKit/537.36 (KHTML, like Gecko) Chrome/73.0.3661.1 Safari/537.36", "Accept-Charset": "ISO-8859-1,utf-8;q=0.7,*;q=0.7", "Accept": "text/html,application/xhtml+xml,application/xml;q=0.9,*/*;q=0.8", "Accept-Encoding": "gzip, deflate", "Accept-Language": "en-us,en;q=0.5"}}, {"asr": null, "filesize": 17973138, "format_id": "137", "format_note": "1080p", "fps": 24, "height": 1080, "quality": 5, "tbr": 630.122, "url": "https://rr4---sn-0opoxu-ihv6.googlevideo.com/videoplayback?expire=1670688948&ei=VFyUY7v6H5aIkgadip_oCQ&ip=189.173.225.87&id=o-AFW7Rp6p35vgAk6-fBL-fAQ0-SfRE7H3WnB1rShRkFlV&itag=137&aitags=133%2C134%2C135%2C136%2C137%2C160%2C242%2C243%2C244%2C247%2C248%2C278&source=youtube&requiressl=yes&mh=ik&mm=31%2C29&mn=sn-0opoxu-ihv6%2Csn-q4fl6nz6&ms=au%2Crdu&mv=m&mvi=4&pcm2cms=yes&pl=24&gcr=mx&initcwndbps=896250&vprv=1&mime=video%2Fmp4&ns=2bGxXg8GVqTE0hLH61FT-WgJ&gir=yes&clen=17973138&dur=228.186&lmt=1605402269368985&mt=1670666961&fvip=4&keepalive=yes&fexp=24001373%2C24007246&c=WEB&txp=1311222&n=WHwbY3eV_UXa3-_mb&sparams=expire%2Cei%2Cip%2Cid%2Caitags%2Csource%2Crequiressl%2Cgcr%2Cvprv%2Cmime%2Cns%2Cgir%2Cclen%2Cdur%2Clmt&lsparams=mh%2Cmm%2Cmn%2Cms%2Cmv%2Cmvi%2Cpcm2cms%2Cpl%2Cinitcwndbps&lsig=AG3C_xAwRAIgQsw_ulA_ZWslZbs_ZUx1JZW57pqSQGAV0IBr9HMuFvgCIDaNX5LE7il7Ug43A-tfAB27sGhd5vmnHZhBek0m_vup&sig=AOq0QJ8wRQIgRM0cpy4dW9tjZfIeVMxEGU2NkFo2bwsXD_FP5lvuqoQCIQDgE8ivIJ9cNspy0OQioLZAdpup76grmQ3fzRj107W8vQ==", "width": 1920, "ext": "mp4", "vcodec": "avc1.640028", "acodec": "none", "vbr": 630.122, "downloader_options": {"http_chunk_size": 10485760}, "container": "mp4_dash", "format": "137 - 1920x1080 (1080p)", "protocol": "https", "http_headers": {"User-Agent": "Mozilla/5.0 (Windows NT 10.0; Win64; x64) AppleWebKit/537.36 (KHTML, like Gecko) Chrome/73.0.3661.1 Safari/537.36", "Accept-Charset": "ISO-8859-1,utf-8;q=0.7,*;q=0.7", "Accept": "text/html,application/xhtml+xml,application/xml;q=0.9,*/*;q=0.8", "Accept-Encoding": "gzip, deflate", "Accept-Language": "en-us,en;q=0.5"}}, {"asr": 22050, "filesize": null, "format_id": "18", "format_note": "360p", "fps": 24, "height": 360, "quality": 2, "tbr": 120.306, "url": "https://rr4---sn-0opoxu-ihv6.googlevideo.com/videoplayback?expire=1670688948&ei=VFyUY7v6H5aIkgadip_oCQ&ip=189.173.225.87&id=o-AFW7Rp6p35vgAk6-fBL-fAQ0-SfRE7H3WnB1rShRkFlV&itag=18&source=youtube&requiressl=yes&mh=ik&mm=31%2C29&mn=sn-0opoxu-ihv6%2Csn-q4fl6nz6&ms=au%2Crdu&mv=m&mvi=4&pcm2cms=yes&pl=24&gcr=mx&initcwndbps=896250&vprv=1&xtags=heaudio%3Dtrue&mime=video%2Fmp4&ns=4pMNh7VrTCHLPp6mH0B63Z4J&cnr=14&ratebypass=yes&dur=228.298&lmt=1657938868930461&mt=1670666961&fvip=4&fexp=24001373%2C24007246&c=WEB&txp=1318224&n=v_lZGb82OMqD2OfBI&sparams=expire%2Cei%2Cip%2Cid%2Citag%2Csource%2Crequiressl%2Cgcr%2Cvprv%2Cxtags%2Cmime%2Cns%2Ccnr%2Cratebypass%2Cdur%2Clmt&lsparams=mh%2Cmm%2Cmn%2Cms%2Cmv%2Cmvi%2Cpcm2cms%2Cpl%2Cinitcwndbps&lsig=AG3C_xAwRgIhAIwzx8Ii97WUwTyXZShB8eoEI36fWk7EDvSOxaY387xKAiEAgSB8EaIp_2Wbq21OITixPpvhdH_M4oY54KwQdAgcPNo%3D&sig=AOq0QJ8wRQIgWV7SCjCzU3-MDKZuhCJuZUkfs0SRQzYKPD6DIb49T78CIQCMGGMCe4Cf1uNlV9Gn7-CN2hryXRqME_C3HGVro3k0hQ==", "width": 640, "ext": "mp4", "vcodec": "avc1.42001E", "acodec": "mp4a.40.2", "format": "18 - 640x360 (360p)", "protocol": "https", "http_headers": {"User-Agent": "Mozilla/5.0 (Windows NT 10.0; Win64; x64) AppleWebKit/537.36 (KHTML, like Gecko) Chrome/73.0.3661.1 Safari/537.36", "Accept-Charset": "ISO-8859-1,utf-8;q=0.7,*;q=0.7", "Accept": "text/html,application/xhtml+xml,application/xml;q=0.9,*/*;q=0.8", "Accept-Encoding": "gzip, deflate", "Accept-Language": "en-us,en;q=0.5"}}], "thumbnails": [{"height": 94, "url": "https://i.ytimg.com/vi/X6cbmmOJZRA/hqdefault.jpg?sqp=-oaymwEbCKgBEF5IVfKriqkDDggBFQAAiEIYAXABwAEG&rs=AOn4CLBRktHPRgavH8DAqpPsOM1O2FAUEw", "width": 168, "resolution": "168x94", "id": "0"}, {"height": 110, "url": "https://i.ytimg.com/vi/X6cbmmOJZRA/hqdefault.jpg?sqp=-oaymwEbCMQBEG5IVfKriqkDDggBFQAAiEIYAXABwAEG&rs=AOn4CLBB0-LqZp-Sy1XNE7UWx1vGRUnUUA", "width": 196, "resolution": "196x110", "id": "1"}, {"height": 138, "url": "https://i.ytimg.com/vi/X6cbmmOJZRA/hqdefault.jpg?sqp=-oaymwEcCPYBEIoBSFXyq4qpAw4IARUAAIhCGAFwAcABBg==&rs=AOn4CLCqeFg8ahYDqfK2aUyR0zFmUl-NJA", "width": 246, "resolution": "246x138", "id": "2"}, {"height": 188, "url": "https://i.ytimg.com/vi/X6cbmmOJZRA/hqdefault.jpg?sqp=-oaymwEcCNACELwBSFXyq4qpAw4IARUAAIhCGAFwAcABBg==&rs=AOn4CLBeDI8uARqyDWidJacL9PuWi5JHPg", "width": 336, "resolution": "336x188", "id": "3"}, {"height": 1080, "url": "https://i.ytimg.com/vi/X6cbmmOJZRA/maxresdefault.jpg", "width": 1920, "resolution": "1920x1080", "id": "4"}], "description": "Music video by Conjunto Primavera performing Muero (Audio). \u00a9 2019 UMG Recordings, Inc.\n\nhttp://vevo.ly/XYwbUH", "upload_date": "20190714", "uploader": "ConjuntoPrimavraVEVO", "uploader_id": "ConjuntoPrimavraVEVO", "uploader_url": "http://www.youtube.com/user/ConjuntoPrimavraVEVO", "channel_id": "UClAfSxKoD4qxOQ4s3DvoaTA", "channel_url": "https://www.youtube.com/channel/UClAfSxKoD4qxOQ4s3DvoaTA", "duration": 228, "view_count": 1285088, "average_rating": null, "age_limit": 0, "webpage_url": "https://www.youtube.com/watch?v=X6cbmmOJZRA", "categories": ["Music"], "tags": ["Conjunto", "Primavera", "Muero", "(Audio)", "UMLE", "Fonovisa", "Latin", "Regional", "Mexican"], "is_live": null, "channel": "Conjunto Primavera", "extractor": "youtube", "webpage_url_basename": "watch", "extractor_key": "Youtube", "playlist": null, "playlist_index": null, "thumbnail": "https://i.ytimg.com/vi/X6cbmmOJZRA/maxresdefault.jpg", "display_id": "X6cbmmOJZRA", "asr": 22050, "filesize": null, "format_id": "18", "format_note": "360p", "fps": 24, "height": 360, "quality": 2, "tbr": 120.306, "url": "https://rr4---sn-0opoxu-ihv6.googlevideo.com/videoplayback?expire=1670688948&ei=VFyUY7v6H5aIkgadip_oCQ&ip=189.173.225.87&id=o-AFW7Rp6p35vgAk6-fBL-fAQ0-SfRE7H3WnB1rShRkFlV&itag=18&source=youtube&requiressl=yes&mh=ik&mm=31%2C29&mn=sn-0opoxu-ihv6%2Csn-q4fl6nz6&ms=au%2Crdu&mv=m&mvi=4&pcm2cms=yes&pl=24&gcr=mx&initcwndbps=896250&vprv=1&xtags=heaudio%3Dtrue&mime=video%2Fmp4&ns=4pMNh7VrTCHLPp6mH0B63Z4J&cnr=14&ratebypass=yes&dur=228.298&lmt=1657938868930461&mt=1670666961&fvip=4&fexp=24001373%2C24007246&c=WEB&txp=1318224&n=v_lZGb82OMqD2OfBI&sparams=expire%2Cei%2Cip%2Cid%2Citag%2Csource%2Crequiressl%2Cgcr%2Cvprv%2Cxtags%2Cmime%2Cns%2Ccnr%2Cratebypass%2Cdur%2Clmt&lsparams=mh%2Cmm%2Cmn%2Cms%2Cmv%2Cmvi%2Cpcm2cms%2Cpl%2Cinitcwndbps&lsig=AG3C_xAwRgIhAIwzx8Ii97WUwTyXZShB8eoEI36fWk7EDvSOxaY387xKAiEAgSB8EaIp_2Wbq21OITixPpvhdH_M4oY54KwQdAgcPNo%3D&sig=AOq0QJ8wRQIgWV7SCjCzU3-MDKZuhCJuZUkfs0SRQzYKPD6DIb49T78CIQCMGGMCe4Cf1uNlV9Gn7-CN2hryXRqME_C3HGVro3k0hQ==", "width": 640, "ext": "mp4", "vcodec": "avc1.42001E", "acodec": "mp4a.40.2", "format": "18 - 640x360 (360p)", "protocol": "https", "http_headers": {"User-Agent": "Mozilla/5.0 (Windows NT 10.0; Win64; x64) AppleWebKit/537.36 (KHTML, like Gecko) Chrome/73.0.3661.1 Safari/537.36", "Accept-Charset": "ISO-8859-1,utf-8;q=0.7,*;q=0.7", "Accept": "text/html,application/xhtml+xml,application/xml;q=0.9,*/*;q=0.8", "Accept-Encoding": "gzip, deflate", "Accept-Language": "en-us,en;q=0.5"}, "fulltitle": "Conjunto Primavera - Muero (Audio)", "_filename": "Conjunto Primavera - Muero (Audio)-X6cbmmOJZRA.mp4"}